evidence/__init__.py
evidence/__main__.py
evidence_with_ease-1.1.3.dist-info/LICENSE
evidence_with_ease-1.1.3.dist-info/METADATA
evidence_with_ease-1.1.3.dist-info/WHEEL
evidence_with_ease-1.1.3.dist-info/entry_points.txt
evidence_with_ease-1.1.3.dist-info/top_level.txt
evidence_with_ease-1.1.3.dist-info/RECORD
