Metadata-Version: 2.1
Name: evidence-with-ease
Version: 1.1.3
Summary: A nifty Python tool for expediting evidence printing.
Home-page: https://github.com/mrbossosity/evidence
Author: mrbossosity
Author-email: mrbossosity@gmail.com
License: UNKNOWN
Platform: UNKNOWN
Requires-Dist: PyPDF2
Requires-Dist: beautifulsoup4
Requires-Dist: lxml
Requires-Dist: pdfkit
Requires-Dist: requests
